{"title":"FLO ─ New Track","url":"https://www.music-flo.com/new/track?sortType=KPOP","favicon":"https://www.music-flo.com/favicon.ico","elements":[{"contents":"<!--fragment#65d8e88d6b#head--> NCT 127 <!--fragment#65d8e88d6b#tail-->","retrieved":1639768957722,"image":"https://cdn.music-flo.com/image/v2/album/860/131/07/04/407131860_61b9be43_o.jpg?1639562820528/dims/resize/1000x1000/quality/90"},{"contents":"<!--fragment#28f7ed8b8#head--> 라붐 (LABOUM) <!--fragment#28f7ed8b8#tail-->","retrieved":1639768957722,"image":"https://cdn.music-flo.com/image/v2/album/986/137/07/04/407137986_61bbdb77_s.jpg?1639701370125/dims/resize/1000x1000/quality/90"},{"contents":"<!--fragment#11c92ed4e4c#head--> 디셈버 (December) <!--fragment#11c92ed4e4c#tail-->","retrieved":1639768957722,"image":"https://cdn.music-flo.com/image/v2/album/511/139/07/04/407139511_61baf637_s.jpg?1639642684007/dims/resize/140x140/quality/90"},{"contents":"<!--fragment#7509d3ee61#head--> DAKSHOOD <!--fragment#7509d3ee61#tail-->","retrieved":1639768957722,"image":"https://cdn.music-flo.com/image/v2/album/720/122/07/04/407122720_61b82048_s.jpg?1639456843189/dims/resize/140x140/quality/90"},{"contents":"<!--fragment#151ca166dea#head--> 허영생 <!--fragment#151ca166dea#tail-->","retrieved":1639768957722,"image":"https://cdn.music-flo.com/image/v2/album/979/138/07/04/407138979_61bad019_s.jpg?1639632922280/dims/resize/200x200/quality/90"},{"contents":"<!--fragment#5f240b7913#head--> 장들레 <!--fragment#5f240b7913#tail-->","retrieved":1639768957722,"image":"https://cdn.music-flo.com/image/v2/album/424/131/07/04/407131424_61b99699_o.jpg?1639552667035/dims/resize/200x200/quality/90"},{"contents":"<!--fragment#173a7153a21#head--> 더 맨 블랙 (THE MAN BLK) <!--fragment#173a7153a21#tail-->","retrieved":1639768957723,"image":"https://cdn.music-flo.com/image/v2/album/052/139/07/04/407139052_61bad4dc_o.jpg?1639634141901/dims/resize/200x200/quality/90"},{"contents":"<!--fragment#10b044a74e2#head--> 진영 <!--fragment#10b044a74e2#tail-->","retrieved":1639768957645},{"contents":"<!--fragment#fa94e61146#head--> 라코스타 (Lacostar) <!--fragment#fa94e61146#tail-->","retrieved":1639768957645},{"contents":"<!--fragment#170c233cb46#head--> Milena (밀레나) <!--fragment#170c233cb46#tail-->","retrieved":1639768957645},{"contents":"<!--fragment#13288956ac6#head--> 래원 (Layone) <!--fragment#13288956ac6#tail-->","retrieved":1639768957645},{"contents":"<!--fragment#15845b96d4c#head--> 김동현 <!--fragment#15845b96d4c#tail-->","retrieved":1639768957645},{"contents":"<!--fragment#a9465bccae#head--> 시루 (SIROO) <!--fragment#a9465bccae#tail-->","retrieved":1639768957645},{"contents":"<!--fragment#66b3973b2e#head--> Dirty Diggs <!--fragment#66b3973b2e#tail-->","retrieved":1639768957645},{"contents":"<!--fragment#efcbcc5dc4#head--> 재주소년소녀 <!--fragment#efcbcc5dc4#tail-->","retrieved":1639768957645},{"contents":"<!--fragment#164700bfd4e#head--> 이루마 <!--fragment#164700bfd4e#tail-->","retrieved":1639768957645},{"contents":"<!--fragment#162d1efde3d#head--> 안예슬 <!--fragment#162d1efde3d#tail-->","retrieved":1639768957645},{"contents":"<!--fragment#16be514032c#head--> 젠토 (Gento) <!--fragment#16be514032c#tail-->","retrieved":1639768957645},{"contents":"<!--fragment#16e251b7f68#head--> 우리같은사람들 <!--fragment#16e251b7f68#tail-->","retrieved":1639768957645},{"contents":"<!--fragment#94684c58e8#head--> 트라이비(TRI.BE) <!--fragment#94684c58e8#tail-->","retrieved":1639768957645},{"contents":"<!--fragment#6d3e4e4d35#head--> WEN <!--fragment#6d3e4e4d35#tail-->","retrieved":1639768957645},{"contents":"<!--fragment#4bc00567f6#head--> 차우주 <!--fragment#4bc00567f6#tail-->","retrieved":1639768957645},{"contents":"<!--fragment#3e23e5ad45#head--> 정승환 <!--fragment#3e23e5ad45#tail-->","retrieved":1639768957645},{"contents":"<!--fragment#23d7bb61f9#head--> 한경일 <!--fragment#23d7bb61f9#tail-->","retrieved":1639768957653},{"contents":"<!--fragment#97d056789f#head--> 식보이 (Sikboy) <!--fragment#97d056789f#tail-->","retrieved":1639768957653},{"contents":"<!--fragment#3f86a0f1a0#head--> 최유리 <!--fragment#3f86a0f1a0#tail-->","retrieved":1639768957653},{"contents":"<!--fragment#177cbcbfa15#head--> 오열 <!--fragment#177cbcbfa15#tail-->","retrieved":1639768957670},{"contents":"<!--fragment#5e4a0bc2af#head--> 푸디토리움 <!--fragment#5e4a0bc2af#tail-->","retrieved":1639768957670},{"contents":"<!--fragment#6400f69977#head--> 빌런즈 (VILLAINZ) <!--fragment#6400f69977#tail-->","retrieved":1639768957670},{"contents":"<!--fragment#5dda836a46#head--> CHEEZE (치즈) <!--fragment#5dda836a46#tail-->","retrieved":1639768957670},{"contents":"<!--fragment#cff76ee0c9#head--> 박문치 <!--fragment#cff76ee0c9#tail-->","retrieved":1639768957670},{"contents":"<!--fragment#48445f4ee6#head--> 극한데뷔 야생돌 <!--fragment#48445f4ee6#tail-->","retrieved":1639768957670},{"contents":"<!--fragment#10061f22154#head--> 더더 <!--fragment#10061f22154#tail-->","retrieved":1639768957670},{"contents":"<!--fragment#26acae1054#head--> Glen Check <!--fragment#26acae1054#tail-->","retrieved":1639768957670},{"contents":"<!--fragment#13f98ee7473#head--> 주현미 재즈 프로젝트 <!--fragment#13f98ee7473#tail-->","retrieved":1639768957670},{"contents":"<!--fragment#2029f2545e#head--> 두번째 별 <!--fragment#2029f2545e#tail-->","retrieved":1639768957670},{"contents":"<!--fragment#c7deccba8#head--> 그래쓰 (GRASS) <!--fragment#c7deccba8#tail-->","retrieved":1639768957677},{"contents":"<!--fragment#12595e60959#head--> 이구이 (IGWI) <!--fragment#12595e60959#tail-->","retrieved":1639768957677},{"contents":"<!--fragment#593ff8c4ca#head--> 안소미 <!--fragment#593ff8c4ca#tail-->","retrieved":1639768957677},{"contents":"<!--fragment#648eb2ca3b#head--> 서율 <!--fragment#648eb2ca3b#tail-->","retrieved":1639768957677},{"contents":"<!--fragment#117accae806#head--> Jimmy Brown <!--fragment#117accae806#tail-->","retrieved":1639768957677},{"contents":"<!--fragment#723a1212f9#head--> G. Nine <!--fragment#723a1212f9#tail-->","retrieved":1639768957677},{"contents":"<!--fragment#bc878ae36d#head--> 임서원 <!--fragment#bc878ae36d#tail-->","retrieved":1639768957677},{"contents":"<!--fragment#14808eca6bb#head--> APOKI <!--fragment#14808eca6bb#tail-->","retrieved":1639768957677},{"contents":"<!--fragment#516b10a7a8#head--> entoy <!--fragment#516b10a7a8#tail-->","retrieved":1639768957700},{"contents":"<!--fragment#11f46af5dcc#head--> Anonymous Artists <!--fragment#11f46af5dcc#tail-->","retrieved":1639768957700},{"contents":"<!--fragment#55310e7460#head--> 김하은 <!--fragment#55310e7460#tail-->","retrieved":1639768957701},{"contents":"<!--fragment#9ee7657f3e#head--> 금잔디 <!--fragment#9ee7657f3e#tail-->","retrieved":1639768957701},{"contents":"<!--fragment#b515b57a91#head--> THE PIECES(더 피스) <!--fragment#b515b57a91#tail-->","retrieved":1639768957701},{"contents":"<!--fragment#e7e6082db5#head--> ABOUT (어바웃) <!--fragment#e7e6082db5#tail-->","retrieved":1639768957701},{"contents":"<!--fragment#a824c14d55#head--> 정예원 (YEWON) <!--fragment#a824c14d55#tail-->","retrieved":1639768957701},{"contents":"<!--fragment#71228551ab#head--> 김우진 <!--fragment#71228551ab#tail-->","retrieved":1639768957701},{"contents":"<!--fragment#fcd433076#head--> 헤이맨 (Hey Men) <!--fragment#fcd433076#tail-->","retrieved":1639768957701},{"contents":"<!--fragment#1393c5612ff#head--> CHILDDIAHN (차일디안) <!--fragment#1393c5612ff#tail-->","retrieved":1639768957701},{"contents":"<!--fragment#c8fb402e71#head--> 레이니 <!--fragment#c8fb402e71#tail-->","retrieved":1639768957701},{"contents":"<!--fragment#1ff8d87abd#head--> 마블제이 <!--fragment#1ff8d87abd#tail-->","retrieved":1639768957701},{"contents":"<!--fragment#2f7c1fa5a5#head--> 남경운 <!--fragment#2f7c1fa5a5#tail-->","retrieved":1639768957701},{"contents":"<!--fragment#16f13ceaba5#head--> I'll (아일) <!--fragment#16f13ceaba5#tail-->","retrieved":1639768957701},{"contents":"<!--fragment#276f69a256#head--> 서인영 <!--fragment#276f69a256#tail-->","retrieved":1639768957701},{"contents":"<!--fragment#a6600f00f4#head--> 탄 (매드몬스터) <!--fragment#a6600f00f4#tail-->","retrieved":1639768957701},{"contents":"<!--fragment#15629a86153#head--> 지산 <!--fragment#15629a86153#tail-->","retrieved":1639768957701},{"contents":"<!--fragment#16b6561d8ab#head--> 영재 (Youngjae) <!--fragment#16b6561d8ab#tail-->","retrieved":1639768957713},{"contents":"<!--fragment#12525f87905#head--> SHIRT <!--fragment#12525f87905#tail-->","retrieved":1639768957713},{"contents":"<!--fragment#c1b99bc8e8#head--> Cherry Coke <!--fragment#c1b99bc8e8#tail-->","retrieved":1639768957713},{"contents":"<!--fragment#6e84c99d20#head--> NCT U <!--fragment#6e84c99d20#tail-->","retrieved":1639768957713},{"contents":"<!--fragment#cb1d18c189#head--> 종한 (JONGHAN) <!--fragment#cb1d18c189#tail-->","retrieved":1639768957713},{"contents":"<!--fragment#10fd2d23d7e#head--> 도파민 (DoPaMine) <!--fragment#10fd2d23d7e#tail-->","retrieved":1639768957713},{"contents":"<!--fragment#159613b0b8#head--> 림지 (LimJi) <!--fragment#159613b0b8#tail-->","retrieved":1639768957713},{"contents":"<!--fragment#10c9930d4da#head--> LOGI (로기) <!--fragment#10c9930d4da#tail-->","retrieved":1639768957713},{"contents":"<!--fragment#28fa0f372f#head--> Iony (아이오니) <!--fragment#28fa0f372f#tail-->","retrieved":1639768957714},{"contents":"<!--fragment#f085336f51#head--> Beer <!--fragment#f085336f51#tail-->","retrieved":1639768957714},{"contents":"<!--fragment#16fffbd411e#head--> 조영남 <!--fragment#16fffbd411e#tail-->","retrieved":1639768957714},{"contents":"<!--fragment#13e3b2bafa1#head--> 태인(TAIN) <!--fragment#13e3b2bafa1#tail-->","retrieved":1639768957714},{"contents":"<!--fragment#1630d12da07#head--> 별은 <!--fragment#1630d12da07#tail-->","retrieved":1639768957714},{"contents":"<!--fragment#67547396c#head--> 원도 <!--fragment#67547396c#tail-->","retrieved":1639768957721},{"contents":"<!--fragment#a7af1d0d59#head--> 극한데뷔 야생돌 <!--fragment#a7af1d0d59#tail-->","retrieved":1639768957722},{"contents":"<!--fragment#76a0d4aa32#head--> 원셋 (1set) <!--fragment#76a0d4aa32#tail-->","retrieved":1639768957723},{"contents":"<!--fragment#fe03161209#head--> 다비 (DAVII) <!--fragment#fe03161209#tail-->","retrieved":1639768957724},{"contents":"<!--fragment#13744b738f0#head--> KozyPop <!--fragment#13744b738f0#tail-->","retrieved":1639768957725},{"contents":"<!--fragment#55d06b76e8#head--> 릴러말즈 (Leellamarz) <!--fragment#55d06b76e8#tail-->","retrieved":1639768957726},{"contents":"<!--fragment#40e0802d02#head--> 호미들 <!--fragment#40e0802d02#tail-->","retrieved":1639768957727},{"contents":"<!--fragment#3aaa229c10#head--> 파사딕 (Posadic) <!--fragment#3aaa229c10#tail-->","retrieved":1639768957727},{"contents":"<!--fragment#606a7fae4e#head--> 오소연 <!--fragment#606a7fae4e#tail-->","retrieved":1639768957728},{"contents":"<!--fragment#178ed12dfb5#head--> 김주리 <!--fragment#178ed12dfb5#tail-->","retrieved":1639768957729},{"contents":"<!--fragment#750719b5f8#head--> TSUN (티썬) <!--fragment#750719b5f8#tail-->","retrieved":1639768957730},{"contents":"<!--fragment#ef968257ab#head--> 하성운 <!--fragment#ef968257ab#tail-->","retrieved":1639768957732},{"contents":"<!--fragment#ab429849dc#head--> 강동훈 <!--fragment#ab429849dc#tail-->","retrieved":1639768957733},{"contents":"<!--fragment#f3c2b39f2b#head--> 자칼 (Jackal) <!--fragment#f3c2b39f2b#tail-->","retrieved":1639768957734},{"contents":"<!--fragment#16e0d8064aa#head--> Billlie <!--fragment#16e0d8064aa#tail-->","retrieved":1639768957734},{"contents":"<!--fragment#49b88178c5#head--> 황카키 <!--fragment#49b88178c5#tail-->","retrieved":1639768957735},{"contents":"<!--fragment#14b9d5e71b0#head--> OSSH <!--fragment#14b9d5e71b0#tail-->","retrieved":1639768957736},{"contents":"<!--fragment#16911296dfe#head--> 세우 인 윤훼이 <!--fragment#16911296dfe#tail-->","retrieved":1639768957736},{"contents":"<!--fragment#169076f3ab5#head--> 신나라 <!--fragment#169076f3ab5#tail-->","retrieved":1639768957737},{"contents":"<!--fragment#10897f0c61#head--> PIXY (픽시) <!--fragment#10897f0c61#tail-->","retrieved":1639768957737},{"contents":"<!--fragment#ef2b48c482#head--> oid (오이드) <!--fragment#ef2b48c482#tail-->","retrieved":1639768957738},{"contents":"<!--fragment#e0f83086b2#head--> 박현서 <!--fragment#e0f83086b2#tail-->","retrieved":1639768957745},{"contents":"<!--fragment#be73564ba1#head--> 박현수 <!--fragment#be73564ba1#tail-->","retrieved":1639768957746},{"contents":"<!--fragment#17e38b9579#head--> Kim Jeong_uk(김정욱) <!--fragment#17e38b9579#tail-->","retrieved":1639768957747},{"contents":"<!--fragment#66fc9ad882#head--> Sebastian Park <!--fragment#66fc9ad882#tail-->","retrieved":1639768957747},{"contents":"<!--fragment#146db3cbd8a#head--> DNOPF <!--fragment#146db3cbd8a#tail-->","retrieved":1639768957750}]}