{"title":"FLO ─ New Track","url":"https://www.music-flo.com/new/track?sortType=KPOP","favicon":"https://www.music-flo.com/favicon.ico","elements":[{"title":"FAKE RAPPERS KILLER (Feat. northfacegawd)","contents":"<!--fragment#2cfe716a2#head-->수퍼비<!--fragment#2cfe716a2#tail-->","link":"https://www.music-flo.com/detail/album/edzzadiny/albumtrack","retrieved":1632993954737,"image":"https://cdn.music-flo.com/image/v2/album/329/610/06/04/406610329_6153f547_s.jpg?1632892234237/dims/resize/140x140/quality/90"},{"title":"직진","contents":"<!--fragment#7759e6682#head-->딘딘 (DINDIN)<!--fragment#7759e6682#tail-->","link":"https://www.music-flo.com/detail/album/edzzaneii/albumtrack","retrieved":1632993954738,"image":"https://cdn.music-flo.com/image/v2/album/433/612/06/04/406612433_615418d4_s.jpg?1632901333391/dims/resize/140x140/quality/90"},{"title":"Remember","contents":"<!--fragment#115b172a8f5#head-->유라 (youra)<!--fragment#115b172a8f5#tail-->","link":"https://www.music-flo.com/detail/album/edzlylnhn/albumtrack","retrieved":1632993954738,"image":"https://cdn.music-flo.com/image/v2/album/282/595/06/04/406595282_61529eaa_o.jpg?1632804524062/dims/resize/140x140/quality/90"},{"title":"내 사람입니다 (2021)","contents":"<!--fragment#14a5e180c5a#head-->김경록<!--fragment#14a5e180c5a#tail-->","link":"https://www.music-flo.com/detail/album/edzzdyain/albumtrack","retrieved":1632993954739,"image":"https://cdn.music-flo.com/image/v2/album/132/609/06/04/406609132_6153dd00_s.jpg?1632886019681/dims/resize/140x140/quality/90"},{"title":"DISTORTION","contents":"<!--fragment#11f2b958955#head-->조하 (JOHA)<!--fragment#11f2b958955#tail-->","link":"https://www.music-flo.com/detail/album/edzzadooi/albumtrack","retrieved":1632993954741,"image":"https://cdn.music-flo.com/image/v2/album/773/610/06/04/406610773_6153fcae_s.jpg?1632894127000/dims/resize/x140/quality/90"},{"title":"Hot & Cold (2021)","contents":"<!--fragment#112d34e4fcd#head-->ARIAZ (아리아즈)<!--fragment#112d34e4fcd#tail-->","link":"https://www.music-flo.com/detail/album/edzzdhyno/albumtrack","retrieved":1632993954769,"image":"https://cdn.music-flo.com/image/v2/album/927/608/06/04/406608927_6153d6bf_s.jpg?1632884418142/dims/resize/140x140/quality/90"},{"title":"놀이터","contents":"<!--fragment#4f39990047#head-->한기란<!--fragment#4f39990047#tail-->","link":"https://www.music-flo.com/detail/album/edzlyyzol/albumtrack","retrieved":1632993954773,"image":"https://cdn.music-flo.com/image/v2/album/675/599/06/04/406599675_61544821_o.jpg?1632913443016/dims/resize/140x140/quality/90"},{"title":"아무도 될 수 없다는 게","contents":"<!--fragment#d80bd6d51d#head-->원써겐 (1sagain)<!--fragment#d80bd6d51d#tail-->","link":"https://www.music-flo.com/detail/album/edzzandnz/albumtrack","retrieved":1632993954643},{"title":"혹시나 하는 말","contents":"<!--fragment#d21fea7db5#head-->결 (KYUL)<!--fragment#d21fea7db5#tail-->","link":"https://www.music-flo.com/detail/album/edzlhdoil/albumtrack","retrieved":1632972278009},{"title":"밤이 좋아서 (Feat. 용훈 of 원위(ONEWE))","contents":"<!--fragment#3177de3b6f#head-->런치박스 (lunCHbox)<!--fragment#3177de3b6f#tail-->","link":"https://www.music-flo.com/detail/album/edzlyyyie/albumtrack","retrieved":1632993954643},{"title":"Us, in Memories","contents":"<!--fragment#da8113f6cb#head-->Janet Suhh (자넷서)<!--fragment#da8113f6cb#tail-->","link":"https://www.music-flo.com/detail/album/edzzdyale/albumtrack","retrieved":1632972278012},{"title":"폭주 feat. BUSYNESSBOY (prod.King South G)","contents":"<!--fragment#123fc185873#head-->KING SOUTH G<!--fragment#123fc185873#tail-->","link":"https://www.music-flo.com/detail/album/edzzanlhz/albumtrack","retrieved":1632993954645},{"title":"주말 (Vocal 지묵)","contents":"<!--fragment#811a088be3#head-->그네<!--fragment#811a088be3#tail-->","link":"https://www.music-flo.com/detail/album/edzlylyio/albumtrack","retrieved":1632993954645},{"title":"BANDS TO THA ROOF","contents":"<!--fragment#9033e59644#head-->Mac9 (맥나인)<!--fragment#9033e59644#tail-->","link":"https://www.music-flo.com/detail/album/edzlyhloe/albumtrack","retrieved":1632993954645},{"title":"이제 헤어지는 건가 봐","contents":"<!--fragment#b5861affee#head-->오현우<!--fragment#b5861affee#tail-->","link":"https://www.music-flo.com/detail/album/edzlylzaz/albumtrack","retrieved":1632972278011},{"title":"꿈처럼 포근한 거야 (Feat. 모닝커피 (Morning Coffee))","contents":"<!--fragment#15903270f74#head-->브런치 레시피 (Brunch recipe)<!--fragment#15903270f74#tail-->","link":"https://www.music-flo.com/detail/album/edzzadnzd/albumtrack","retrieved":1632972277930},{"title":"너와 나 (Feat. 소울 크라이)","contents":"<!--fragment#43901e358c#head-->마멀레이드 키친 (Marmalade Kitchen)<!--fragment#43901e358c#tail-->","link":"https://www.music-flo.com/detail/album/edzzadenl/albumtrack","retrieved":1632972277913},{"title":"morse moss(skit)","contents":"<!--fragment#3b2dca633e#head-->한국사람<!--fragment#3b2dca633e#tail-->","link":"https://www.music-flo.com/detail/album/edzzdnhzo/albumtrack","retrieved":1632972277995},{"title":"사랑은 언제나 목마르다 (N번째 연애 X 이해리 (다비치))","contents":"<!--fragment#743d50f2d8#head-->이해리<!--fragment#743d50f2d8#tail-->","link":"https://www.music-flo.com/detail/album/edzlyondz/albumtrack","retrieved":1632907396014},{"title":"헤어진 날의 일기","contents":"<!--fragment#745967c6cd#head-->뱅크<!--fragment#745967c6cd#tail-->","link":"https://www.music-flo.com/detail/album/edzlyydnh/albumtrack","retrieved":1632972277912},{"title":"You Lie So Good","contents":"<!--fragment#aff355f292#head-->오드리노 (Audrey No)<!--fragment#aff355f292#tail-->","link":"https://www.music-flo.com/detail/album/edzzanide/albumtrack","retrieved":1632972277910},{"title":"버디찬스","contents":"<!--fragment#71ca0f415a#head-->신나라<!--fragment#71ca0f415a#tail-->","link":"https://www.music-flo.com/detail/album/edzzadeii/albumtrack","retrieved":1632972278034},{"title":"너와 밤과 별","contents":"<!--fragment#174636cb52d#head-->김새벽<!--fragment#174636cb52d#tail-->","link":"https://www.music-flo.com/detail/album/edzzdhlhh/albumtrack","retrieved":1632972277917},{"title":"처음 만난 그때처럼","contents":"<!--fragment#17745aa87a2#head-->김필<!--fragment#17745aa87a2#tail-->","link":"https://www.music-flo.com/detail/album/edzlyodaa/albumtrack","retrieved":1632907396009},{"title":"I′ll never stop dreaming","contents":"<!--fragment#621e9e3a5e#head-->김준휘<!--fragment#621e9e3a5e#tail-->","link":"https://www.music-flo.com/detail/album/edzzdhooe/albumtrack","retrieved":1632972278014},{"title":"Lover Like Me","contents":"<!--fragment#6aed342e3c#head-->CL<!--fragment#6aed342e3c#tail-->","link":"https://www.music-flo.com/detail/album/edzllaiho/albumtrack","retrieved":1632896920393},{"title":"버리러 가는 길","contents":"<!--fragment#f1cfbd673a#head-->최윤정<!--fragment#f1cfbd673a#tail-->","link":"https://www.music-flo.com/detail/album/edzzaneha/albumtrack","retrieved":1632972277918},{"title":"ICONS","contents":"<!--fragment#4e795971c6#head-->핫이슈 (HOT ISSUE)<!--fragment#4e795971c6#tail-->","link":"https://www.music-flo.com/detail/album/edzlyonly/albumtrack","retrieved":1632907396059},{"title":"Circle","contents":"<!--fragment#735eb7e13a#head-->WEEKDAY<!--fragment#735eb7e13a#tail-->","link":"https://www.music-flo.com/detail/album/edzzdyaoo/albumtrack","retrieved":1632972277919},{"title":"Perfume","contents":"<!--fragment#9d77234bb3#head-->멜로우 키친<!--fragment#9d77234bb3#tail-->","link":"https://www.music-flo.com/detail/album/edzlyoaee/albumtrack","retrieved":1632972277915},{"title":"행복으로 키운 오렌지","contents":"<!--fragment#fd9766d8bf#head-->신온유<!--fragment#fd9766d8bf#tail-->","link":"https://www.music-flo.com/detail/album/edzlyiyod/albumtrack","retrieved":1632907395920},{"title":"20세기 사람들 (Vocal by Zion.T)","contents":"<!--fragment#d12187b6f9#head-->강승원<!--fragment#d12187b6f9#tail-->","link":"https://www.music-flo.com/detail/album/edzlyoaei/albumtrack","retrieved":1632907396016},{"title":"Sincere Love (Explicit Ver.)","contents":"<!--fragment#49c16db1ae#head-->entoy<!--fragment#49c16db1ae#tail-->","link":"https://www.music-flo.com/detail/album/edziznoaa/albumtrack","retrieved":1632907395919},{"title":"BEAM","contents":"<!--fragment#5124931dcc#head-->TOMMY YANG<!--fragment#5124931dcc#tail-->","link":"https://www.music-flo.com/detail/album/edzlhaiez/albumtrack","retrieved":1632907396043},{"title":"엄마","contents":"<!--fragment#2cb3c19465#head-->보이킴 (Boy Kim)<!--fragment#2cb3c19465#tail-->","link":"https://www.music-flo.com/detail/album/edzzdyell/albumtrack","retrieved":1632972277933},{"title":"악연 (Dark Dream)","contents":"<!--fragment#237589f71c#head-->엘라스트 (E'LAST)<!--fragment#237589f71c#tail-->","link":"https://www.music-flo.com/detail/album/edzlonihd/albumtrack","retrieved":1632907396065},{"title":"먼지","contents":"<!--fragment#efe37cc459#head-->화자<!--fragment#efe37cc459#tail-->","link":"https://www.music-flo.com/detail/album/edzlhayli/albumtrack","retrieved":1632896920394},{"title":"스르르(zZZ)(feat.홍의진)","contents":"<!--fragment#ac7417f47b#head-->Soup<!--fragment#ac7417f47b#tail-->","link":"https://www.music-flo.com/detail/album/edzlyeohe/albumtrack","retrieved":1632907395920},{"title":"STAR","contents":"<!--fragment#95f5ffaf36#head-->KINIE.K (키니케이)<!--fragment#95f5ffaf36#tail-->","link":"https://www.music-flo.com/detail/album/edzlyeyzl/albumtrack","retrieved":1632907395920},{"title":"봄날","contents":"<!--fragment#13b242b5ea0#head-->naru (나루)<!--fragment#13b242b5ea0#tail-->","link":"https://www.music-flo.com/detail/album/edzlhnhly/albumtrack","retrieved":1632896920396},{"title":"인디언","contents":"<!--fragment#d950fa1680#head-->Re.JACK(리잭)<!--fragment#d950fa1680#tail-->","link":"https://www.music-flo.com/detail/album/edzlhnlle/albumtrack","retrieved":1632907395923},{"title":"Alone (Feat. Austn)","contents":"<!--fragment#19bf7008b7#head-->숨셔<!--fragment#19bf7008b7#tail-->","link":"https://www.music-flo.com/detail/album/edzlyolhz/albumtrack","retrieved":1632896920440},{"title":"별이다","contents":"<!--fragment#f2dc19b2d2#head-->버블 시스터즈<!--fragment#f2dc19b2d2#tail-->","link":"https://www.music-flo.com/detail/album/edzlhieza/albumtrack","retrieved":1632896920397},{"title":"뱃노래","contents":"<!--fragment#c941722c9c#head-->sEODo BAND (서도밴드)<!--fragment#c941722c9c#tail-->","link":"https://www.music-flo.com/detail/album/edzlyzaze/albumtrack","retrieved":1632896920363},{"title":"Drama","contents":"<!--fragment#632a930de4#head-->나웅재 (NAUNGJAE)<!--fragment#632a930de4#tail-->","link":"https://www.music-flo.com/detail/album/edzlyylee/albumtrack","retrieved":1632907395927},{"title":"10 Minutes","contents":"<!--fragment#1f4e7be4ba#head-->원슈타인<!--fragment#1f4e7be4ba#tail-->","link":"https://www.music-flo.com/detail/album/edzlyleny/albumtrack","retrieved":1632896920440},{"title":"Easty (feat. SIKBOY)","contents":"<!--fragment#11f6e6b6ee8#head-->Yonge Jaundice (영 잔디스)<!--fragment#11f6e6b6ee8#tail-->","link":"https://www.music-flo.com/detail/album/edzlyeone/albumtrack","retrieved":1632896920453},{"title":"Little Things (Feat. YELO)","contents":"<!--fragment#e487512153#head-->TJ Monterde<!--fragment#e487512153#tail-->","link":"https://www.music-flo.com/detail/album/edzloadyz/albumtrack","retrieved":1632907395932},{"title":"니가 좋아했으면 해","contents":"<!--fragment#13f5349dba4#head-->우디 (Woody)<!--fragment#13f5349dba4#tail-->","link":"https://www.music-flo.com/detail/album/edzlhdzdd/albumtrack","retrieved":1632896920362},{"title":"Hate Me","contents":"<!--fragment#ca84e2be3a#head-->오아 (OA)<!--fragment#ca84e2be3a#tail-->","link":"https://www.music-flo.com/detail/album/edzlyholh/albumtrack","retrieved":1632896920361},{"title":"TWILIGHT (Ooh)","contents":"<!--fragment#64f5a09871#head-->미카엘 (M!KYLE)<!--fragment#64f5a09871#tail-->","link":"https://www.music-flo.com/detail/album/edzllhydi/albumtrack","retrieved":1632896920360},{"title":"보내 (BONE)","contents":"<!--fragment#bf0c4062b4#head-->배준렬 (BJR)<!--fragment#bf0c4062b4#tail-->","link":"https://www.music-flo.com/detail/album/edzlyloyd/albumtrack","retrieved":1632896920366},{"title":"Blessed (Feat. GSoul)","contents":"<!--fragment#135b886c8dd#head-->THAMA<!--fragment#135b886c8dd#tail-->","link":"https://www.music-flo.com/detail/album/edzlhdzii/albumtrack","retrieved":1632896920364},{"title":"사랑하고 싶다","contents":"<!--fragment#265bda99d0#head-->유승우<!--fragment#265bda99d0#tail-->","link":"https://www.music-flo.com/detail/album/edzlhiayh/albumtrack","retrieved":1632896920365},{"title":"나에게로 Come To Me","contents":"<!--fragment#136d67cad2f#head-->니쥬 (nijuu)<!--fragment#136d67cad2f#tail-->","link":"https://www.music-flo.com/detail/album/edzlonini/albumtrack","retrieved":1632896920375},{"title":"사랑은 갑자기 내 맘에 들어와","contents":"<!--fragment#452c9b4d9b#head-->천소아<!--fragment#452c9b4d9b#tail-->","link":"https://www.music-flo.com/detail/album/edzlyezdl/albumtrack","retrieved":1632896920373},{"title":"Queen","contents":"<!--fragment#8cbaab0217#head-->Paxy (팍시)<!--fragment#8cbaab0217#tail-->","link":"https://www.music-flo.com/detail/album/edzlynyna/albumtrack","retrieved":1632896920369},{"title":"머리 없어도","contents":"<!--fragment#68ac0928#head-->스칼렛킴<!--fragment#68ac0928#tail-->","link":"https://www.music-flo.com/detail/album/edzlhnany/albumtrack","retrieved":1632896920368},{"title":"이별 없는 날","contents":"<!--fragment#f9e8e99833#head-->정유진<!--fragment#f9e8e99833#tail-->","link":"https://www.music-flo.com/detail/album/edzlhdydn/albumtrack","retrieved":1632896920368},{"title":"콩깍지","contents":"<!--fragment#a7f3bdfe8e#head-->싸이퍼 (Ciipher)<!--fragment#a7f3bdfe8e#tail-->","link":"https://www.music-flo.com/detail/album/edzlhianl/albumtrack","retrieved":1632896920370},{"title":"너를 부를때…(Prod. PATEKO(파테코),Kid Wine)","contents":"<!--fragment#13119e17742#head-->WetBoy<!--fragment#13119e17742#tail-->","link":"https://www.music-flo.com/detail/album/edzloahln/albumtrack","retrieved":1632896920371},{"title":"7000RPM","contents":"<!--fragment#121f5465324#head-->KARDI (카디)<!--fragment#121f5465324#tail-->","link":"https://www.music-flo.com/detail/album/edzlhneey/albumtrack","retrieved":1632896920376},{"title":"조용히 눈을 감고 (Band ver.)","contents":"<!--fragment#8dfddf49ec#head-->모던다락방<!--fragment#8dfddf49ec#tail-->","link":"https://www.music-flo.com/detail/album/edzlhdzla/albumtrack","retrieved":1632896920374},{"title":"RESONATE","contents":"<!--fragment#1375030d01c#head-->WANNA (워나)<!--fragment#1375030d01c#tail-->","link":"https://www.music-flo.com/detail/album/edzlhdyye/albumtrack","retrieved":1632896920367},{"title":"그냥 웃자","contents":"<!--fragment#25fd78ab8c#head-->김다현<!--fragment#25fd78ab8c#tail-->","link":"https://www.music-flo.com/detail/album/edzlhnlzi/albumtrack","retrieved":1632896920377},{"title":"Move! (With. 루루, 라라)","contents":"<!--fragment#e78f852b8f#head-->박문치<!--fragment#e78f852b8f#tail-->","link":"https://www.music-flo.com/detail/album/edzlhanhe/albumtrack","retrieved":1632896920378},{"title":"Closer (Feat. ARON)","contents":"<!--fragment#1531249f23d#head-->Choisul<!--fragment#1531249f23d#tail-->","link":"https://www.music-flo.com/detail/album/edzlhddhz/albumtrack","retrieved":1632896920379},{"title":"Oh My Daddy","contents":"<!--fragment#4e1e3307fe#head-->제이블랙 &amp; 제이핑크 (J BLACK &amp; J PINK)<!--fragment#4e1e3307fe#tail-->","link":"https://www.music-flo.com/detail/album/edzloeyoh/albumtrack","retrieved":1632896920379},{"title":"BAD LOVE","contents":"<!--fragment#3d4b286838#head-->키 (KEY)<!--fragment#3d4b286838#tail-->","link":"https://www.music-flo.com/detail/album/edzlhadey/albumtrack","retrieved":1632896920380},{"title":"겨울바다","contents":"<!--fragment#6454ca3109#head-->최재현<!--fragment#6454ca3109#tail-->","link":"https://www.music-flo.com/detail/album/edzloeoio/albumtrack","retrieved":1632896920380},{"title":"Now carti on my wrist whats next","contents":"<!--fragment#1bba1e74e5#head-->zzuno だいすき!<!--fragment#1bba1e74e5#tail-->","link":"https://www.music-flo.com/detail/album/edzlhidaz/albumtrack","retrieved":1632896920381},{"title":"Align","contents":"<!--fragment#12e202caad1#head-->Viral Affair<!--fragment#12e202caad1#tail-->","link":"https://www.music-flo.com/detail/album/edzlhalih/albumtrack","retrieved":1632896920381},{"title":"문득 (Duet with 송희진)","contents":"<!--fragment#8505a65f93#head-->도운 (DAY6)<!--fragment#8505a65f93#tail-->","link":"https://www.music-flo.com/detail/album/edzlhdyzh/albumtrack","retrieved":1632896920382},{"title":"21g","contents":"<!--fragment#10f432fe0ea#head-->Meek Drib<!--fragment#10f432fe0ea#tail-->","link":"https://www.music-flo.com/detail/album/edzlhadzd/albumtrack","retrieved":1632896920383},{"title":"우린 마를 리 없었지","contents":"<!--fragment#dfbd70013b#head-->겸 (GYE0M)<!--fragment#dfbd70013b#tail-->","link":"https://www.music-flo.com/detail/album/edzlollly/albumtrack","retrieved":1632896920383},{"title":"Tree","contents":"<!--fragment#fa84064c6e#head-->오월오일 ( 五月五日 )<!--fragment#fa84064c6e#tail-->","link":"https://www.music-flo.com/detail/album/edzloleoe/albumtrack","retrieved":1632896920384},{"title":"Misfit (Prod. GRIO)","contents":"<!--fragment#17084636bab#head-->CLIQUE<!--fragment#17084636bab#tail-->","link":"https://www.music-flo.com/detail/album/edzloeeyy/albumtrack","retrieved":1632896920384},{"title":"CHERRY","contents":"<!--fragment#cac4e901de#head-->AB6IX (에이비식스)<!--fragment#cac4e901de#tail-->","link":"https://www.music-flo.com/detail/album/edzlhazol/albumtrack","retrieved":1632896920385},{"title":"She got somethin'","contents":"<!--fragment#c637e1cfa5#head-->몰리디<!--fragment#c637e1cfa5#tail-->","link":"https://www.music-flo.com/detail/album/edzlhdzia/albumtrack","retrieved":1632896920385},{"title":"Just Reply","contents":"<!--fragment#70894f060#head-->뷰티핸섬<!--fragment#70894f060#tail-->","link":"https://www.music-flo.com/detail/album/edzlhdzno/albumtrack","retrieved":1632896920386},{"title":"잘 자 (Feat. VEL)","contents":"<!--fragment#11e04f81e7d#head-->if.iwere (입하월)<!--fragment#11e04f81e7d#tail-->","link":"https://www.music-flo.com/detail/album/edzlhdzyo/albumtrack","retrieved":1632896920386},{"title":"너의 눈물이 나의 눈을 적실 때","contents":"<!--fragment#7a8a311609#head-->에일리(Ailee)<!--fragment#7a8a311609#tail-->","link":"https://www.music-flo.com/detail/album/edzlhdlld/albumtrack","retrieved":1632896920386},{"title":"강강술래 (경주 & 안동) (Feat. sogumm) (Prod. GRAY)","contents":"<!--fragment#1590655606f#head-->우원재<!--fragment#1590655606f#tail-->","link":"https://www.music-flo.com/detail/album/edzlolede/albumtrack","retrieved":1632896920386},{"title":"쿵쿵쿵","contents":"<!--fragment#14135f752d#head-->Liquor (리쿼)<!--fragment#14135f752d#tail-->","link":"https://www.music-flo.com/detail/album/edzlhneei/albumtrack","retrieved":1632896920387},{"title":"Same Things Anymore","contents":"<!--fragment#707e7496e7#head-->Uzuhan (우주한)<!--fragment#707e7496e7#tail-->","link":"https://www.music-flo.com/detail/album/edzlhdzad/albumtrack","retrieved":1632896920387},{"title":"아름다운 걸","contents":"<!--fragment#5d8e2de0ef#head-->백퍼센트<!--fragment#5d8e2de0ef#tail-->","link":"https://www.music-flo.com/detail/album/edzlhdydo/albumtrack","retrieved":1632896920387},{"title":"웃음소리 (Vocal by 임단우)","contents":"<!--fragment#a30f9753bb#head-->이진우<!--fragment#a30f9753bb#tail-->","link":"https://www.music-flo.com/detail/album/edzllnzai/albumtrack","retrieved":1632896920387},{"title":"Promise","contents":"<!--fragment#ac63fadb06#head-->태헌<!--fragment#ac63fadb06#tail-->","link":"https://www.music-flo.com/detail/album/edzlhnnzz/albumtrack","retrieved":1632896920388},{"title":"아인슈타인 (feat. Louie) (Prod. Badtree)","contents":"<!--fragment#3ec0e45893#head-->스카프 (SC4F)<!--fragment#3ec0e45893#tail-->","link":"https://www.music-flo.com/detail/album/edzloeeoz/albumtrack","retrieved":1632896920388},{"title":"기다릴게","contents":"<!--fragment#347c68fab3#head-->후아유<!--fragment#347c68fab3#tail-->","link":"https://www.music-flo.com/detail/album/edzloliiz/albumtrack","retrieved":1632896920389},{"title":"Sticker","contents":"<!--fragment#779e62642c#head-->Seiren 8<!--fragment#779e62642c#tail-->","link":"https://www.music-flo.com/detail/album/edzlhadno/albumtrack","retrieved":1632896920389},{"title":"Flower (Feat. 김하은, centipede)","contents":"<!--fragment#e9cc30030f#head-->공든 (ODEUN)<!--fragment#e9cc30030f#tail-->","link":"https://www.music-flo.com/detail/album/edzlhdzha/albumtrack","retrieved":1632896920389},{"title":"초대하지 않은 손님","contents":"<!--fragment#11387837745#head-->안희수(Heesu Ahn)<!--fragment#11387837745#tail-->","link":"https://www.music-flo.com/detail/album/edzlooido/albumtrack","retrieved":1632896920390},{"title":"Echo (Feat. Omega Sapien)","contents":"<!--fragment#56135fd38e#head-->이수호<!--fragment#56135fd38e#tail-->","link":"https://www.music-flo.com/detail/album/edzllhyde/albumtrack","retrieved":1632896920398},{"title":"Santa Monica","contents":"<!--fragment#105b7960d82#head-->NIK<!--fragment#105b7960d82#tail-->","link":"https://www.music-flo.com/detail/album/edzlooidz/albumtrack","retrieved":1632896920399},{"title":"사랑하지 않았을 거야","contents":"<!--fragment#592bef3102#head-->장희원<!--fragment#592bef3102#tail-->","link":"https://www.music-flo.com/detail/album/edzlollzn/albumtrack","retrieved":1632896920400},{"title":"Fly Away (feat. Eily)","contents":"<!--fragment#76eb302194#head-->lofi<!--fragment#76eb302194#tail-->","link":"https://www.music-flo.com/detail/album/edzllhyei/albumtrack","retrieved":1632896920401},{"title":"tonight","contents":"<!--fragment#121c05b79a#head-->Jimmy Brown<!--fragment#121c05b79a#tail-->","link":"https://www.music-flo.com/detail/album/edzllhzdh/albumtrack","retrieved":1632896920402},{"title":"in the air","contents":"<!--fragment#ed752ddbd7#head-->Won Jang<!--fragment#ed752ddbd7#tail-->","link":"https://www.music-flo.com/detail/album/edzloeioy/albumtrack","retrieved":1632896920404},{"title":"저 인형 (Feat. 안병웅)","contents":"<!--fragment#2a63d4aa03#head-->b!ni<!--fragment#2a63d4aa03#tail-->","link":"https://www.music-flo.com/detail/album/edzlolnhy/albumtrack","retrieved":1632896920405}]}